{
    "version": "0.9.21",
    "description": "A music player inspired by Winamp that supports Plex, Jellyfin, Emby, Navidrome and Subsonic",
    "homepage": "https://github.com/rekkyrosso/ampcast",
    "license": "GPL-3.0-or-later",
    "architecture": {
        "64bit": {
            "url": "https://github.com/rekkyrosso/ampcast/releases/download/v0.9.21/ampcast-0.9.21-win-x64.zip",
            "hash": "431b04342d0d1b3b4e497602681099e769b740bde62ba393c6347fd2c34dcd45"
        }
    },
    "shortcuts": [
        [
            "ampcast.exe",
            "Ampcast"
        ]
    ],
    "checkver": "github",
    "autoupdate": {
        "architecture": {
            "64bit": {
                "url": "https://github.com/rekkyrosso/ampcast/releases/download/v$version/ampcast-$version-win-x64.zip"
            }
        }
    }
}
