{
    "version": "7.0.0",
    "description": "Database manager for MySQL, PostgreSQL, SQL Server, MongoDB, SQLite and others. Runs under Windows, Linux, Mac or as web application",
    "homepage": "https://github.com/dbgate/dbgate",
    "license": "GPL-3.0-or-later",
    "architecture": {
        "64bit": {
            "url": "https://github.com/dbgate/dbgate/releases/download/v7.0.0/dbgate-7.0.0-win_x64.zip",
            "hash": "432db7df41d316f07f507a14528acf6baba394a985108d8fd5213cad846e2b15"
        },
        "arm64": {
            "url": "https://github.com/dbgate/dbgate/releases/download/v7.0.0/dbgate-7.0.0-win_arm64.zip",
            "hash": "07333c9761c7c21960f5e0234b3edf3f4c9b384769bc3d1eb8cbc8c6f6cac739"
        }
    },
    "extract_to": "",
    "shortcuts": [
        [
            "DbGate.exe",
            "DbGate"
        ]
    ],
    "checkver": "github",
    "autoupdate": {
        "architecture": {
            "64bit": {
                "url": "https://github.com/dbgate/dbgate/releases/download/v$version/dbgate-$version-win_x64.zip"
            },
            "arm64": {
                "url": "https://github.com/dbgate/dbgate/releases/download/v$version/dbgate-$version-win_arm64.zip"
            }
        }
    }
}
