{
    "version": "1.65.0",
    "description": "a better dotenv–from the creator of `dotenv`",
    "homepage": "https://github.com/dotenvx/dotenvx",
    "license": "BSD-3-Clause",
    "architecture": {
        "64bit": {
            "url": "https://github.com/dotenvx/dotenvx/releases/download/v1.65.0/dotenvx-windows-amd64.zip",
            "hash": "92fc36b6fad31c308a598677f0a8fb6c3465946a328762abd2fdfba85c7f74da"
        }
    },
    "bin": "dotenvx.exe",
    "checkver": "github",
    "autoupdate": {
        "architecture": {
            "64bit": {
                "url": "https://github.com/dotenvx/dotenvx/releases/download/v$version/dotenvx-windows-amd64.zip"
            }
        }
    }
}
