{
    "version": "1.11.2",
    "description": "a better dotenv–from the creator of `dotenv`",
    "homepage": "https://github.com/dotenvx/dotenvx",
    "license": "BSD-3-Clause",
    "architecture": {
        "64bit": {
            "url": "https://github.com/dotenvx/dotenvx/releases/download/v1.11.2/dotenvx-windows-amd64.zip",
            "hash": "8138e50ed00455688372020fcd7138dd1d1e69d9dc407b45d976433ddea211b9"
        }
    },
    "bin": "dotenvx.exe",
    "checkver": "github",
    "autoupdate": {
        "architecture": {
            "64bit": {
                "url": "https://github.com/dotenvx/dotenvx/releases/download/v$version/dotenvx-windows-amd64.zip"
            }
        }
    }
}
