{
    "version": "2.8.2",
    "description": "Unit and Integration Test generation for Developers. Generate tests and stubs for your application that actually work",
    "homepage": "https://github.com/keploy/keploy",
    "license": "Apache-2.0",
    "architecture": {
        "64bit": {
            "url": "https://github.com/keploy/keploy/releases/download/v2.8.2/keploy_windows_amd64.tar.gz",
            "hash": "499a26b8db58ac68ddbb30c090bc8cd10419edd29d4bae1ee82e81c38a37b305"
        },
        "arm64": {
            "url": "https://github.com/keploy/keploy/releases/download/v2.8.2/keploy_windows_arm64.tar.gz",
            "hash": "36e19c5cdfcadd7738c7604ff187bd908026bb7d05a6f04e52cc3efacd888a41"
        }
    },
    "bin": "keploy.exe",
    "checkver": "github",
    "autoupdate": {
        "architecture": {
            "64bit": {
                "url": "https://github.com/keploy/keploy/releases/download/v$version/keploy_windows_amd64.tar.gz"
            },
            "arm64": {
                "url": "https://github.com/keploy/keploy/releases/download/v$version/keploy_windows_arm64.tar.gz"
            }
        }
    }
}
