{
    "version": "0.12.0",
    "description": "Web based real-time log viewer. Stream ANY content to a web UI with autogenerated filters. Parse any format with TypeScript",
    "homepage": "https://github.com/logdyhq/logdy-core",
    "license": "Apache-2.0",
    "architecture": {
        "64bit": {
            "url": "https://github.com/logdyhq/logdy-core/releases/download/v0.12.0/logdy_windows_amd64.exe",
            "hash": "ac4c5fea491bf94433cfbd53f5e1cbc20e7a93e6b4788b1112ea6bd3c7b116bc"
        },
        "32bit": {
            "url": "https://github.com/logdyhq/logdy-core/releases/download/v0.12.0/logdy_windows_386.exe",
            "hash": "b0c1a50450b8bf62c0535d66680846246c6f5191549ce076c8ace4bcce10508c"
        }
    },
    "bin": "logdy.exe",
    "checkver": "github",
    "autoupdate": {
        "architecture": {
            "64bit": {
                "url": "https://github.com/logdyhq/logdy-core/releases/download/v$version/logdy_windows_amd64.exe"
            },
            "32bit": {
                "url": "https://github.com/logdyhq/logdy-core/releases/download/v$version/logdy_windows_386.exe"
            }
        }
    }
}
