{
    "version": "2025.610.0",
    "homepage": "https://github.com/Founntain/osuplayer",
    "description": "Official osu!player repository. osu!player is a music player for the game osu! made by Dean 'peppy' Herbert. Written in the cross-platform framework AvaloniaUI",
    "license": "MIT",
    "architecture": {
        "64bit": {
            "url": "https://github.com/Founntain/osuplayer/releases/download/2025.610.0/win-x64.zip",
            "hash": "dbb0f13261dd5f4ca9d9607626645c0d6a60ca2e8f876615569b3b361fc4e242"
        },
        "32bit": {
            "url": "https://github.com/Founntain/osuplayer/releases/download/2025.610.0/win-x86.zip",
            "hash": "31f49d1d6700e95d878ea8f2c729ebbceb8944691f17ca7f47de88913a472697"
        }
    },
    "shortcuts": [
        [
            "OsuPlayer.exe",
            "osu! Player"
        ]
    ],
    "checkver": "github",
    "autoupdate": {
        "architecture": {
            "64bit": {
                "url": "https://github.com/Founntain/osuplayer/releases/download/$version/win-x64.zip"
            },
            "32bit": {
                "url": "https://github.com/Founntain/osuplayer/releases/download/$version/win-x86.zip"
            }
        }
    }
}
