{
    "$schema": "https://raw.githubusercontent.com/ScoopInstaller/Scoop/master/schema.json",
    "version": "7.22.0",
    "description": "A Utility CLI for AI Coding Agents",
    "homepage": "https://github.com/dyoshikawa/rulesync",
    "license": "MIT",
    "architecture": {
        "64bit": {
            "url": "https://github.com/dyoshikawa/rulesync/releases/download/v7.22.0/rulesync-windows-x64.exe#/rulesync.exe",
            "hash": "173adcd2cd3abbe24750d5218ca2a316dea2fabe5784789eea5b8711ea2520da"
        }
    },
    "bin": "rulesync.exe",
    "checkver": "github",
    "autoupdate": {
        "architecture": {
            "64bit": {
                "url": "https://github.com/dyoshikawa/rulesync/releases/download/v$version/rulesync-windows-x64.exe#/rulesync.exe"
            }
        }
    }
}
