{
    "$schema": "https://raw.githubusercontent.com/ScoopInstaller/Scoop/master/schema.json",
    "version": "9.4.0",
    "description": "A Utility CLI for AI Coding Agents",
    "homepage": "https://github.com/dyoshikawa/rulesync",
    "license": "MIT",
    "architecture": {
        "64bit": {
            "url": "https://github.com/dyoshikawa/rulesync/releases/download/v9.4.0/rulesync-windows-x64.exe#/rulesync.exe",
            "hash": "5050d44b056fa88558ef8ac330adc33395f172000fd41027f785676d9c78c164"
        }
    },
    "bin": "rulesync.exe",
    "checkver": "github",
    "autoupdate": {
        "architecture": {
            "64bit": {
                "url": "https://github.com/dyoshikawa/rulesync/releases/download/v$version/rulesync-windows-x64.exe#/rulesync.exe"
            }
        }
    }
}
