{
    "version": "2.12.9",
    "description": "Modern UI for Ansible",
    "homepage": "https://github.com/semaphoreui/semaphore",
    "license": "MIT",
    "notes": "",
    "architecture": {
        "64bit": {
            "url": "https://github.com/semaphoreui/semaphore/releases/download/v2.12.9/semaphore_2.12.9_windows_amd64.zip",
            "hash": "99bf43e28982174d482b0d6f0a51910bc46bebe38c34fde1f152b993d888db11"
        }
    },
    "bin": "semaphore.exe",
    "checkver": "github",
    "autoupdate": {
        "architecture": {
            "64bit": {
                "url": "https://github.com/semaphoreui/semaphore/releases/download/v$version/semaphore_$version_windows_amd64.zip"
            }
        }
    }
}
