{
    "version": "24050601",
    "description": "Advanced WSL launcher / installer. (Win10 FCU x64/arm64 or later.)",
    "homepage": "https://github.com/yuk7/wsldl",
    "license": "MIT",
    "architecture": {
        "64bit": {
            "url": "https://github.com/yuk7/wsldl/releases/download/24050601/wsldl.exe",
            "hash": "533a19fa1aa5e85cae8ba715098428cfb3cb1553d53208cdf9b28b16045a2570"
        },
        "arm64": {
            "url": "https://github.com/yuk7/wsldl/releases/download/24050601/wsldl_arm64.exe#/wsldl.exe",
            "hash": "8d182544822ee18a9b511d4a7b366db59d8c950083875fa49fa84d5636768480"
        }
    },
    "bin": "wsldl.exe",
    "checkver": "github",
    "autoupdate": {
        "architecture": {
            "64bit": {
                "url": "https://github.com/yuk7/wsldl/releases/download/$version/wsldl.exe"
            },
            "arm64": {
                "url": "https://github.com/yuk7/wsldl/releases/download/$version/wsldl_arm64.exe#/wsldl.exe"
            }
        }
    }
}
